LICENSE
README.rst
setup.cfg
setup.py
rxx/__init__.py
rxx/types.py
rxx.egg-info/PKG-INFO
rxx.egg-info/SOURCES.txt
rxx.egg-info/dependency_links.txt
rxx.egg-info/requires.txt
rxx.egg-info/top_level.txt
rxx/internal/__init__.py
rxx/internal/trampoline.py
rxx/observable/__init__.py
rxx/observable/enforce_ordering.py
rxx/pullable/__init__.py
rxx/pullable/pull.py
rxx/pullable/push.py
rxx/pullable/sorted_merge.py
tests/__init__.py