Metadata-Version: 1.2
Name: rxx
Version: 0.2.0
Summary: ReactiveX extensions
Home-page: https://github.com/maki-nage/rxx.git
Author: Romain Picard
Author-email: romain.picard@oakbits.com
License: MIT
Project-URL: Documentation, https://www.makinage.org/doc/rxx/latest/index.html
Platform: any
Classifier: Development Status :: 3 - Alpha
Classifier: License :: OSI Approved :: MIT License
Classifier: Intended Audience :: Developers
Classifier: Programming Language :: Python :: 3
